LICENSE
MANIFEST.in
README.md
README.pypi
pyproject.toml
requirements.txt
setup.py
Orange3_flow.egg-info/PKG-INFO
Orange3_flow.egg-info/SOURCES.txt
Orange3_flow.egg-info/dependency_links.txt
Orange3_flow.egg-info/entry_points.txt
Orange3_flow.egg-info/namespace_packages.txt
Orange3_flow.egg-info/not-zip-safe
Orange3_flow.egg-info/requires.txt
Orange3_flow.egg-info/top_level.txt
orangecontrib/__init__.py
orangecontrib/flow/__init__.py
orangecontrib/flow/tests/__init__.py
orangecontrib/flow/tests/utils.py
orangecontrib/flow/utils/__init__.py
orangecontrib/flow/widgets/__init__.py
orangecontrib/flow/widgets/owgate.py
orangecontrib/flow/widgets/icons/category.svg
orangecontrib/flow/widgets/icons/gate.svg
orangecontrib/flow/widgets/tests/__init__.py
orangecontrib/flow/widgets/tests/test_owgate.py