Metadata-Version: 2.1
Name: Orange3-flow
Version: 0.1.0
Summary: Add-on to help simplify pipelines
License: GPLv3+
Keywords: orange3 add-on,flow
License-File: LICENSE
